aiopypiserver/__init__.py
aiopypiserver/__main__.py
aiopypiserver/webserver.py
aiopypiserver/assets/__init__.py
aiopypiserver/assets/index.html
aiopypiserver/assets/list.html
aiopypiserver/assets/pure.css
aiopypiserver/assets/__pycache__/__init__.cpython-311.pyc
aiopypiserver-0.0.7.dist-info/LICENSE
aiopypiserver-0.0.7.dist-info/METADATA
aiopypiserver-0.0.7.dist-info/WHEEL
aiopypiserver-0.0.7.dist-info/entry_points.txt
aiopypiserver-0.0.7.dist-info/top_level.txt
aiopypiserver-0.0.7.dist-info/RECORD
