Metadata-Version: 2.1
Name: aiopypiserver
Version: 0.0.7
Summary: Like pypiserver, but works behind a proxy with relative href addresses. Uses aiohttp.
Author: Jamie Walton
Project-URL: Homepage, https://github.com/jamie0walton/aiopypiserver
Project-URL: Bug Tracker, https://github.com/jamie0walton/aiopypiserver/issues
Classifier: Programming Language :: Python :: 3
Classifier: License :: OSI Approved :: GNU General Public License v3 (GPLv3)
Classifier: Operating System :: OS Independent
Classifier: Environment :: Console
Classifier: Development Status :: 3 - Alpha
Requires-Python: >=3.9
License-File: LICENSE
Requires-Dist: aiohttp (==3.8.*)
